seriattrs/__init__.py
seriattrs/_db_attrs_converter.py
seriattrs/JsonEncoder/Decoder.py
seriattrs/JsonEncoder/DefaultJsonEncoder.py
seriattrs/JsonEncoder/Encoder.py
seriattrs/JsonEncoder/JsonOperator.py
seriattrs/JsonEncoder/__init__.py
seriattrs/JsonEncoder/default_json_encoder.py
seriattrs/JsonEncoder/Decoders/BytesDecoder.py
seriattrs/JsonEncoder/Decoders/DatetimeDecoder.py
seriattrs/JsonEncoder/Decoders/DecimalDecoder.py
seriattrs/JsonEncoder/Decoders/EnumDecoder.py
seriattrs/JsonEncoder/Decoders/PathDecoder.py
seriattrs/JsonEncoder/Decoders/__init__.py
seriattrs/JsonEncoder/Encoders/AttrsEncoder.py
seriattrs/JsonEncoder/Encoders/BytestEncoder.py
seriattrs/JsonEncoder/Encoders/DataclassEncoder.py
seriattrs/JsonEncoder/Encoders/DatetimeEncoder.py
seriattrs/JsonEncoder/Encoders/DecimalEncoder.py
seriattrs/JsonEncoder/Encoders/EnumEncoder.py
seriattrs/JsonEncoder/Encoders/PathEncoder.py
seriattrs/JsonEncoder/Encoders/__init__.py
seriattrs/db_classes/DbClass.py
seriattrs/db_classes/DbClassCreator.py
seriattrs/db_classes/DbClassLiteral.py
seriattrs/db_classes/__init__.py
seriattrs/db_classes/db_fields/__init__.py
seriattrs/db_classes/db_fields/ints.py
seriattrs/db_classes/db_fields/texts.py
seriattrs-2.2.0.dist-info/LICENSE
seriattrs-2.2.0.dist-info/METADATA
seriattrs-2.2.0.dist-info/WHEEL
seriattrs-2.2.0.dist-info/top_level.txt
seriattrs-2.2.0.dist-info/RECORD
