Metadata-Version: 2.1
Name: seriattrs
Version: 2.2.0
Summary: Unofficial extension of attrs ment to provided default serialization and deserialization options
Home-page: https://github.com/Tesla2000/seriattrs
Author: Tesla2000
Author-email: fratajczak124@gmail.com
Project-URL: Homepage, https://github.com/Tesla2000/seriattrs
Classifier: Programming Language :: Python :: 3
Classifier: License :: OSI Approved :: MIT License
Classifier: Operating System :: OS Independent
Requires-Python: >=3.5
License-File: LICENSE
Requires-Dist: cattrs >=23.2.3
Requires-Dist: attrs >=23.2.0
